odoo/addons/purchase_request_usage_department/README.rst
odoo/addons/purchase_request_usage_department/__init__.py
odoo/addons/purchase_request_usage_department/__manifest__.py
odoo/addons/purchase_request_usage_department/i18n/purchase_request_usage_department.pot
odoo/addons/purchase_request_usage_department/models/__init__.py
odoo/addons/purchase_request_usage_department/models/hr_department.py
odoo/addons/purchase_request_usage_department/models/purchase_request.py
odoo/addons/purchase_request_usage_department/readme/CONTRIBUTORS.rst
odoo/addons/purchase_request_usage_department/readme/CREDITS.rst
odoo/addons/purchase_request_usage_department/readme/DESCRIPTION.rst
odoo/addons/purchase_request_usage_department/readme/USAGE.rst
odoo/addons/purchase_request_usage_department/static/description/icon.png
odoo/addons/purchase_request_usage_department/static/description/index.html
odoo/addons/purchase_request_usage_department/tests/__init__.py
odoo/addons/purchase_request_usage_department/tests/test_purchase_request_usage_department.py
odoo/addons/purchase_request_usage_department/views/hr_department_view.xml
odoo12_addon_purchase_request_usage_department-12.0.1.0.1.dist-info/METADATA
odoo12_addon_purchase_request_usage_department-12.0.1.0.1.dist-info/WHEEL
odoo12_addon_purchase_request_usage_department-12.0.1.0.1.dist-info/top_level.txt
odoo12_addon_purchase_request_usage_department-12.0.1.0.1.dist-info/RECORD
